drl/__init__.py
drl/dqn.py
drl/ppo.py
drl/sac.py
drl/version.py
drl-0.0.1.dist-info/METADATA
drl-0.0.1.dist-info/WHEEL
drl-0.0.1.dist-info/top_level.txt
drl-0.0.1.dist-info/RECORD
