Metadata-Version: 2.1
Name: drl
Version: 0.0.1
Summary: drl
Home-page: http://github.com/zhiqingxiao/drl/
Author: Zhiqing Xiao
Author-email: xzq.xiaozhiqing@gmail.com
Classifier: Programming Language :: Python
Classifier: Intended Audience :: Science/Research
